.gitignore
MANIFEST.in
README.rst
setup.cfg
setup.py
docs/HISTORY.txt
docs/LICENSE.GPL
docs/LICENSE.txt
docs/MANUAL.txt
raptus/__init__.py
raptus.article.slider.egg-info/PKG-INFO
raptus.article.slider.egg-info/SOURCES.txt
raptus.article.slider.egg-info/dependency_links.txt
raptus.article.slider.egg-info/entry_points.txt
raptus.article.slider.egg-info/namespace_packages.txt
raptus.article.slider.egg-info/not-zip-safe
raptus.article.slider.egg-info/requires.txt
raptus.article.slider.egg-info/top_level.txt
raptus/article/__init__.py
raptus/article/slider/__init__.py
raptus/article/slider/configure.zcml
raptus/article/slider/setuphandlers.py
raptus/article/slider/browser/__init__.py
raptus/article/slider/browser/configure.zcml
raptus/article/slider/browser/slider.gif
raptus/article/slider/browser/slider.pt
raptus/article/slider/browser/slider.py
raptus/article/slider/browser/slider_teaser.gif
raptus/article/slider/i18n/raptus.article-de.mo
raptus/article/slider/i18n/raptus.article-de.po
raptus/article/slider/i18n/raptus.article.pot
raptus/article/slider/profiles/default/cssregistry.xml
raptus/article/slider/profiles/default/metadata.xml
raptus/article/slider/profiles/default/propertiestool.xml
raptus/article/slider/profiles/default/raptus.article.slider_install.txt
raptus/article/slider/profiles/default/skins.xml
raptus/article/slider/profiles/default/viewlets.xml
raptus/article/slider/skins/raptus_article_slider/raptus.article.slider.css.dtml