Metadata-Version: 1.1
Name: raptus.article.slider
Version: 1.0a2
Summary: Provides a component which displays the contained articles in a slider
Home-page: https://github.com/Raptus/raptus.article.slider
Author: Raptus AG
Author-email: dev@raptus.com
License: GPL
Platform: UNKNOWN
Classifier: Programming Language :: Python
Classifier: Topic :: Software Development :: Libraries :: Python Modules
